{"frontend_js_css_数组的交集、并集、差集.md":"c387e240","frontend_bagu_index.md":"ece197af","frontend_js_css_url-add-param.md":"9767fd62","frontend_js_css_index.md":"d9834c6d","frontend_open_why-front.md":"75b47be2","frontend_open_index.md":"b9d3507c","frontend_js_css_settimeout准时.md":"fb440990","frontend_js_css_每隔时间段执行一次函数.md":"358900a7","frontend_js_css_promise链式中断.md":"6a5ab5b3","frontend_js_css_匹配手机号.md":"10e9615d","frontend_js_css_promise.all带并发限制.md":"6a549ca7","frontend_index.md":"2f1c119e","frontend_js_css_url-parse.md":"4abc0a01","frontend_js_css_myinterval.md":"8c7d97ad","frontend_js_css_promise.retry.md":"6def35a5","frontend_js_css_promise.all.md":"3353d533","frontend_js_css_交通灯.md":"8ef037d1","frontend_open_how-learn.md":"ff346b4c","frontend_js_css_promise.race.md":"72a468c6","frontend_open_promise.all.md":"8d63c5d9","markdown-examples.md":"a06e3401","frontend_js_css_promise计时器.md":"c1273b59","frontend_open_book.md":"314b80a1","frontend_js_css_promise.all即使有一个请求错误，依旧能返回所有请求.md":"c025a3f9","kt_index.md":"8d78a40f","frontend_js_css_underline-camelcase.md":"059a9072","frontend_open_front-backend-diff.md":"43841de8","index.md":"ab78d1bc","frontend_js_css_如果上一个请求未完成，则不响应.md":"cbda33bc","frontend_js_css_promise.all顺序执行.md":"0edc9f6b"}
